{
    ".playerHands[0].elementVisibility[1].False": 31097,
    ".playerHands[0].elementVisibility.False": 53646,
    ".playerHands[0].elementVisibility[3].False": 25379,
    ".playerHands[0].components[0].cardSuite.CRAB": 607,
    ".playerHands[0].components[0].cardType.DUO": 2395,
    ".playerHands[0].components.cardSuite.CRAB": 1698,
    ".playerHands[0].components.cardType.DUO": 6958,
    ".playerHands[0].components.type.CARD": 17882,
    ".playerHands.elementVisibility[0].False": 108932,
    ".playerHands.elementVisibility.True": 67387,
    ".playerHands.components.color.GREY": 5478,
    ".playerHands.components.cardSuite.CRAB": 7511,
    ".playerHands.components.type.CARD": 67387,
    ".discardPile2.components.cardType.DUO": 3459,
    ".discardPile2.components.type.CARD": 4875,
    ".drawPile.components.color.ORANGE": 3804,
    ".drawPile.components.cardSuite.SAILOR": 11086,
    ".drawPile.components.cardType.MERMAID": 15180,
    ".drawPile.components.cardType.DUO": 126747,
    ".drawPile.components[3].cardType.COLLECTOR": 1477,
    ".drawPile.components.componentName.YELLOW OCTOPUS COLLECTOR": 3669,
    ".drawPile.components.cardSuite.BOAT": 33559,
    ".drawPile.components.componentName.YELLOW BOAT DUO": 7260,
    ".drawPile.components[5].color.BLACK": 664,
    ".drawPile.components.componentName.YELLOW SHELL COLLECTOR": 3647,
    ".drawPile.components.cardSuite.SHARK": 18374,
    ".drawPile.components[8].cardSuite.SHELL": 572,
    ".drawPile.components.componentName.GREEN CRAB DUO": 3715,
    ".drawPile.components.componentName.GREY FISH MULTIPLIER": 3759,
    ".drawPile.components[14].cardType.DUO": 3128,
    ".drawPile.components.componentName.LIGHT_BLUE BOAT DUO": 7571,
    ".drawPile.components.color.PURPLE": 14767,
    ".drawPile.components.componentName.PURPLE PENGUIN COLLECTOR": 3683,
    ".drawPile.components[16].type.CARD": 5371,
    ".drawPile.components.componentName.GREEN SHELL COLLECTOR": 3765,
    ".drawPile.components.componentName.BLUE CRAB DUO": 7548,
    ".drawPile.components[22].cardType.DUO": 2924,
    ".drawPile.components[22].type.CARD": 5051,
    ".drawPile.components[23].cardSuite.BOAT": 738,
    ".drawPile.components.componentName.YELLOW FISH DUO": 3652,
    ".drawPile.components[28].cardType.DUO": 2568,
    ".drawPile.components[29].color.BLUE": 636,
    ".drawPile.components[31].type.CARD": 3946,
    ".drawPile.components.componentName.BLUE BOAT DUO": 7440,
    ".drawPile.components.componentName.LIGHT_BLUE CRAB DUO": 7493,
    ".drawPile.components[34].cardSuite.CRAB": 521,
    ".drawPile.components.componentName.BLACK CRAB DUO": 3709,
    ".drawPile.components.componentName.LIGHT_BLUE FISH DUO": 3813,
    ".drawPile.components[40].cardType.DUO": 1560,
    ".drawPile.components.componentName.LIGHT_BLUE OCTOPUS COLLECTOR": 3658,
    ".drawPile.components.componentName.LIGHT_ORANGE PENGUIN COLLECTOR": 3646,
    ".drawPile.components.componentName.GREEN SHARK DUO": 3744,
    ".drawPile.components.componentName.GREEN PENGUIN MULTIPLIER": 3690,
    ".drawPile.components.componentName.PINK SAILOR COLLECTOR": 3587,
    ".drawPile.components.componentName.PURPLE SHARK DUO": 3698,
    ".protectedHands[1].False": 4834,
    ".turnOwner.0": 2720,
    ".firstPlayer.0": 2902,
    ".playerHands[0].components.cardSuite.SWIMMER": 911,
    ".playerHands.components[0].color.LIGHT_BLUE": 3177,
    ".playerHands[1].elementVisibility[0][3].False": 4896,
    ".playerHands[1].elementVisibility.False": 49674,
    ".playerHands[1].elementVisibility.True": 16558,
    ".playerHands[1].elementVisibility[3].False": 23332,
    ".playerHands[1].components[0].color.GREEN": 523,
    ".playerHands[1].components[0].cardSuite.FISH": 699,
    ".playerHands[1].components[0].cardType.DUO": 2481,
    ".playerHands[1].components.color.GREEN": 1752,
    ".playerHands[1].components.cardSuite.FISH": 2224,
    ".playerHands[1].components.cardType.DUO": 7280,
    ".playerHands[1].components.type.CARD": 16558,
    ".playerHands.components.color.GREEN": 7009,
    ".playerHands.components.cardSuite.FISH": 8160,
    ".playerHands.components.componentName.GREEN FISH DUO": 807,
    ".playerHands[2].elementVisibility[0].False": 31018,
    ".playerHands[2].elementVisibility.False": 49080,
    ".playerHands[2].elementVisibility[2].True": 19555,
    ".playerHands[2].elementVisibility.True": 16360,
    ".playerHands[2].elementVisibility[3].False": 22918,
    ".playerHands[2].components[0].cardType.COLLECTOR": 1629,
    ".playerHands[2].components.cardSuite.SAILOR": 1071,
    ".playerHands[2].components.cardType.COLLECTOR": 6310,
    ".playerHands.elementVisibility[2].True": 29545,
    ".playerHands[3].elementVisibility[0].False": 31212,
    ".playerHands[3].components[0].cardSuite.MERMAID": 382,
    ".playerHands[3].components.color.WHITE": 1529,
    ".playerHands[3].components.cardType.MERMAID": 1529,
    ".playerHands[3].components.type.CARD": 16587,
    ".playerHands[3].components.componentName.WHITE MERMAID MERMAID": 1529,
    ".playerHands.elementVisibility[3].True": 25804,
    ".playerHands.components[0].color.WHITE": 1662,
    ".discardPile1.components.cardType.COLLECTOR": 1173,
    ".discardPile1.components.type.CARD": 6117,
    ".drawPile.components[0].color.YELLOW": 746,
    ".drawPile.components[0].cardSuite.BOAT": 848,
    ".drawPile.components[0].cardType.DUO": 3153,
    ".drawPile.components[8].cardSuite.BOAT": 787,
    ".drawPile.components[18].cardSuite.CRAB": 821,
    ".drawPile.components[25].componentName.BLUE CRAB DUO": 169,
    ".drawPile.components[28].color.LIGHT_BLUE": 745,
    ".drawPile.components[36].cardSuite.BOAT": 518,
    ".drawPile.components[43].cardType.COLLECTOR": 608,
    ".playerHands[1].components.cardSuite.OCTOPUS": 1924,
    ".playerHands[2].elementVisibility[1].True": 4115,
    ".playerHands[2].components[0].cardType.DUO": 2491,
    ".playerHands[2].components.cardSuite.FISH": 1941,
    ".playerHands[2].components[1].cardType.COLLECTOR": 1503,
    ".playerHands[3].components[0].cardType.DUO": 2537,
    ".playerHands[3].components.color.YELLOW": 2163,
    ".playerHands[3].components.cardSuite.BOAT": 2194,
    ".playerHands[3].components.cardType.DUO": 7441,
    ".playerHands[3].components.componentName.YELLOW BOAT DUO": 540,
    ".playerHands[3].components[1].color.WHITE": 359,
    ".playerHands.components[0].cardSuite.BOAT": 2873,
    ".playerHands.components[1].cardSuite.MERMAID": 1554,
    ".playerDiscards[0].components[0].cardSuite.SHARK": 703,
    ".playerDiscards[0].components[0].cardType.DUO": 2120,
    ".playerDiscards[0].components.cardSuite.SHARK": 1007,
    ".playerDiscards[0].components.type.CARD": 6426,
    ".playerDiscards[0].components.color.LIGHT_BLUE": 1595,
    ".playerDiscards.components[0].cardSuite.SHARK": 2712,
    ".playerDiscards.components[0].type.CARD": 7930,
    ".playerDiscards.components.componentName.BLACK SHARK DUO": 661,
    ".playerDiscards.components[1].cardSuite.SWIMMER": 2712,
    ".playerDiscards.components[1].cardType.DUO": 7930,
    ".playerDiscards.components[1].type.CARD": 7930,
    ".playerDiscards.components.color.LIGHT_BLUE": 5618,
    ".playerDiscards.components.cardSuite.SWIMMER": 3717,
    ".drawPile.components[0].color.BLACK": 670,
    ".drawPile.components[16].color.WHITE": 380,
    ".drawPile.components[35].cardType.MERMAID": 254,
    ".drawPile.components[47].cardType.DUO": 1067,
    ".playerHands[0].components[2].cardType.DUO": 1262,
    ".playerHands.components.cardType.MULTIPLIER": 6137,
    ".playerHands.components.componentName.GREY FISH MULTIPLIER": 1502,
    ".playerHands.components[2].color.GREY": 1090,
    ".playerHands.components[2].cardSuite.CRAB": 1380,
    ".playerHands.components[2].cardType.DUO": 5302,
    ".playerHands[1].components.cardSuite.CRAB": 1923,
    ".playerHands.components.componentName.GREEN CRAB DUO": 862,
    ".playerHands.components[1].color.YELLOW": 2203,
    ".playerHands[2].elementVisibility[2][1].False": 3195,
    ".playerHands[2].elementVisibility[2][2].True": 3195,
    ".playerHands[2].components.color.LIGHT_BLUE": 2341,
    ".playerHands[2].components[2].cardType.COLLECTOR": 1266,
    ".playerHands[2].components[2].type.CARD": 3195,
    ".playerHands.elementVisibility[2][2].True": 3195,
    ".playerHands[3].elementVisibility[2].True": 3247,
    ".playerHands[3].components.cardType.COLLECTOR": 6160,
    ".playerHands[3].components[1].color.YELLOW": 534,
    ".playerHands.components.cardSuite.SHELL": 9526,
    ".playerHands.components[1].cardSuite.BOAT": 2299,
    ".playerHands.components[1].componentName.YELLOW BOAT DUO": 495,
    ".playerHands.components[2].cardSuite.MERMAID": 1357,
    ".discardPile2.components.cardSuite.SWIMMER": 587,
    ".discardPile2.components[1].type.CARD": 1169,
    ".discardPile2.components.cardType.COLLECTOR": 1010,
    ".drawPile.components[0].color.LIGHT_BLUE": 885,
    ".drawPile.components[5].color.BLUE": 841,
    ".drawPile.components[6].cardSuite.OCTOPUS": 470,
    ".drawPile.components[19].cardSuite.OCTOPUS": 446,
    ".drawPile.components[19].cardType.COLLECTOR": 1418,
    ".drawPile.components[31].cardSuite.PENGUIN": 243,
    ".playerHands.components[0].color.PURPLE": 1446,
    ".playerHands.components.color.PURPLE": 5696,
    ".playerHands[1].components[2].cardType.COLLECTOR": 1253,
    ".playerHands.components[0].cardSuite.PENGUIN": 1653,
    ".playerHands.components.cardSuite.PENGUIN": 6628,
    ".playerHands.components.componentName.PURPLE PENGUIN COLLECTOR": 1721,
    ".playerHands.components[2].color.YELLOW": 1714,
    ".playerHands[2].components.color.GREEN": 1801,
    ".playerHands[2].components[1].color.LIGHT_BLUE": 627,
    ".playerHands[3].components.cardSuite.CRAB": 1969,
    ".playerHands.elementVisibility[3][3].True": 2274,
    ".playerHands.components.componentName.BLUE CRAB DUO": 1696,
    ".playerDiscards[0].components[2].cardSuite.SHARK": 220,
    ".playerDiscards[0].components[3].cardType.DUO": 822,
    ".playerDiscards[0].components[3].type.CARD": 822,
    ".playerDiscards.components[0].cardSuite.FISH": 1397,
    ".playerDiscards.components.color.GREEN": 1913,
    ".playerDiscards.components[1].color.BLUE": 1878,
    ".playerDiscards.components[1].cardSuite.FISH": 1397,
    ".playerDiscards.components[1].componentName.BLUE FISH DUO": 426,
    ".playerDiscards.components.color.BLUE": 5389,
    ".playerDiscards.components[2].color.BLACK": 547,
    ".playerDiscards.components[2].cardSuite.SHARK": 775,
    ".playerDiscards.components[3].color.LIGHT_BLUE": 755,
    ".playerDiscards.components[3].type.CARD": 2708,
    ".playerDiscards[2].components[0].color.BLACK": 334,
    ".playerDiscards[2].components.color.BLACK": 876,
    ".playerDiscards[2].components.cardSuite.FISH": 886,
    ".playerDiscards[2].components.type.CARD": 5566,
    ".playerDiscards[2].components[1].cardType.DUO": 1982,
    ".playerDiscards[2].components[1].type.CARD": 1982,
    ".playerDiscards.components.componentName.BLACK FISH DUO": 1182,
    ".playerDiscards.components[1].color.BLACK": 1101,
    ".discardPile1.components[1].type.CARD": 1150,
    ".discardPile2.components[2].type.CARD": 438,
    ".drawPile.components[8].color.LIGHT_BLUE": 923,
    ".drawPile.components[10].cardSuite.CRAB": 839,
    ".drawPile.components[23].cardType.COLLECTOR": 1319,
    ".playerHands[0].components[0].cardSuite.MERMAID": 531,
    ".playerHands[0].components[0].cardType.MERMAID": 531,
    ".playerHands[0].components[0].componentName.WHITE MERMAID MERMAID": 531,
    ".playerHands[0].components.color.WHITE": 2207,
    ".playerHands[0].components.cardSuite.MERMAID": 2207,
    ".playerHands[0].components.cardType.MERMAID": 2207,
    ".playerHands[0].components.componentName.WHITE MERMAID MERMAID": 2207,
    ".playerHands[0].components[3].cardType.DUO": 819,
    ".playerHands.elementVisibility[3][0].True": 2499,
    ".playerHands[1].elementVisibility[3][1].True": 2258,
    ".playerHands[1].components.componentName.PURPLE OCTOPUS COLLECTOR": 343,
    ".playerHands[1].components[2].color.GREEN": 344,
    ".playerHands[1].components[3].color.YELLOW": 274,
    ".playerHands.components[3].color.YELLOW": 1113,
    ".playerHands.components[3].cardSuite.OCTOPUS": 1235,
    ".playerHands[2].elementVisibility[3][1].False": 2186,
    ".playerHands[2].components.cardSuite.BOAT": 2053,
    ".playerHands.elementVisibility[3][2].True": 2186,
    ".playerHands.components[2].color.LIGHT_BLUE": 1884,
    ".playerDiscards[3].components[0].cardType.DUO": 1901,
    ".playerDiscards[3].components[1].cardType.DUO": 1901,
    ".playerDiscards[3].components.color.YELLOW": 981,
    ".playerDiscards.components[0].cardSuite.CRAB": 2028,
    ".playerDiscards.components[0].componentName.BLUE CRAB DUO": 443,
    ".playerDiscards.components.color.YELLOW": 4046,
    ".playerDiscards.components.componentName.YELLOW CRAB DUO": 1304,
    ".drawPile.components[1].color.YELLOW": 750,
    ".drawPile.components[3].color.BLUE": 844,
    ".drawPile.components[24].cardType.COLLECTOR": 1328,
    ".playerHands[0].components.color.YELLOW": 2175,
    ".playerHands[0].components[1].cardSuite.MERMAID": 495,
    ".playerHands[0].components[1].cardType.MERMAID": 495,
    ".playerHands.components[2].color.PURPLE": 1151,
    ".playerHands[1].elementVisibility[4].False": 3954,
    ".playerHands[1].components[0].color.WHITE": 362,
    ".playerHands[1].components[0].cardSuite.MERMAID": 362,
    ".playerHands[1].components[0].cardType.MERMAID": 362,
    ".playerHands[1].components[0].componentName.WHITE MERMAID MERMAID": 362,
    ".playerHands[1].components.color.WHITE": 1389,
    ".playerHands[1].components.cardSuite.MERMAID": 1389,
    ".playerHands[1].components.cardType.MERMAID": 1389,
    ".playerHands[1].components.componentName.WHITE MERMAID MERMAID": 1389,
    ".playerHands.components[3].color.GREEN": 949,
    ".playerHands[2].elementVisibility[4].False": 3747,
    ".playerHands[2].elementVisibility[4][2].True": 1249,
    ".playerHands[2].components.color.PINK": 760,
    ".playerHands[2].components.componentName.PINK PENGUIN COLLECTOR": 425,
    ".playerHands.components.color.PINK": 3235,
    ".playerHands.components.componentName.PINK PENGUIN COLLECTOR": 1594,
    ".playerHands.components[3].color.LIGHT_BLUE": 1250,
    ".playerHands.components[4].cardSuite.SAILOR": 426,
    ".playerHands[3].components.color.LIGHT_ORANGE": 919,
    ".playerHands.components.color.LIGHT_ORANGE": 3803,
    ".playerDiscards[3].components.cardSuite.BOAT": 1312,
    ".playerDiscards[3].components[2].cardType.DUO": 620,
    ".playerDiscards[3].components[3].cardType.DUO": 620,
    ".playerDiscards[3].components[3].type.CARD": 620,
    ".playerDiscards.components.cardSuite.BOAT": 5456,
    ".playerDiscards.components[1].cardSuite.BOAT": 1793,
    ".playerDiscards.components[1].componentName.YELLOW BOAT DUO": 412,
    ".playerDiscards.components[3].color.YELLOW": 515,
    ".drawPile.components[7].color.LIGHT_BLUE": 935,
    ".drawPile.components[14].cardSuite.SAILOR": 288,
    ".drawPile.components[15].color.WHITE": 374,
    ".drawPile.components[21].color.GREEN": 556,
    ".lastChance.3": 158,
    ".protectedHands[0].True": 833,
    ".protectedHands.True": 2770,
    ".protectedHands[3].True": 654,
    ".playerHands[1].components.color.BLUE": 2142,
    ".playerHands[1].components[1].color.WHITE": 337,
    ".playerHands[1].components[1].cardSuite.MERMAID": 337,
    ".playerHands[1].components[1].cardType.MERMAID": 337,
    ".playerHands[1].components[1].componentName.WHITE MERMAID MERMAID": 337,
    ".playerHands[1].components[3].color.PURPLE": 190,
    ".playerHands.elementVisibility[5].False": 6846,
    ".playerHands.elementVisibility[5].True": 2282,
    ".playerHands[2].components.cardSuite.OCTOPUS": 1876,
    ".playerDiscards[2].components[0].cardSuite.BOAT": 405,
    ".playerDiscards[2].components.color.LIGHT_BLUE": 1407,
    ".playerDiscards[2].components.cardSuite.BOAT": 1254,
    ".playerDiscards[2].components[1].cardSuite.BOAT": 405,
    ".playerDiscards[2].components.color.BLUE": 1235,
    ".playerDiscards[2].components.componentName.BLUE BOAT DUO": 298,
    ".playerDiscards[2].components[2].cardType.DUO": 639,
    ".playerDiscards[2].components[2].type.CARD": 639,
    ".playerDiscards.components.componentName.LIGHT_BLUE BOAT DUO": 1394,
    ".drawPile.components[1].color.LIGHT_BLUE": 986,
    ".drawPile.components[18].color.BLUE": 792,
    ".protectedHands[1].True": 638,
    ".protectedHands[2].True": 645,
    ".turnOwner.2": 873,
    ".playerHands[3].components[0].cardSuite.OCTOPUS": 508,
    ".playerHands[3].components.cardSuite.OCTOPUS": 1972,
    ".drawPile.components[6].color.GREEN": 556,
    ".drawPile.components.componentName.GREEN FISH DUO": 3819,
    ".drawPile.components[32].color.YELLOW": 507,
    ".drawPile.components[36].color.YELLOW": 420,
    ".turnOwner.3": 926,
    ".firstPlayer.3": 743,
    ".playerHands.components.componentName.YELLOW CRAB DUO": 1644,
    ".playerHands[1].components.cardSuite.BOAT": 2196,
    ".playerHands[1].components.componentName.BLUE BOAT DUO": 464,
    ".playerHands.components.cardSuite.SHARK": 3774,
    ".playerHands[3].components.color.LIGHT_BLUE": 2461,
    ".discardPile1.components[0].color.BLUE": 659,
    ".drawPile.components[8].cardSuite.MERMAID": 372,
    ".drawPile.components[10].color.BLUE": 792,
    ".drawPile.components[42].color.YELLOW": 369,
    ".playerHands[0].components.color.BLACK": 1605,
    ".playerHands[2].components[0].cardType.MULTIPLIER": 379,
    ".playerHands[2].components.cardType.MULTIPLIER": 1461,
    ".playerHands.components.componentName.GREEN PENGUIN MULTIPLIER": 1548,
    ".playerHands.components.componentName.BLACK SHARK DUO": 795,
    ".playerDiscards.components.componentName.LIGHT_BLUE CRAB DUO": 1345,
    ".drawPile.components[30].cardType.COLLECTOR": 1090,
    ".playerHands[0].components[0].componentName.PINK SAILOR COLLECTOR": 127,
    ".playerHands[0].components.cardType.COLLECTOR": 7175,
    ".playerHands[0].components[1].color.BLACK": 408,
    ".playerHands.components.componentName.PINK SAILOR COLLECTOR": 1641,
    ".playerHands[2].components[0].cardSuite.CRAB": 691,
    ".playerHands[2].components.cardSuite.CRAB": 1921,
    ".playerHands[3].components.componentName.GREY OCTOPUS COLLECTOR": 385,
    ".playerHands[3].components[2].cardSuite.CRAB": 364,
    ".playerHands[3].components[3].cardType.COLLECTOR": 912,
    ".drawPile.components[4].cardSuite.FISH": 698,
    ".drawPile.components[32].color.PURPLE": 256,
    ".playerHands[1].components[0].color.LIGHT_BLUE": 782,
    ".playerHands[1].components.componentName.LIGHT_BLUE SWIMMER DUO": 406,
    ".playerHands[2].components[1].cardSuite.CRAB": 524,
    ".playerHands[3].elementVisibility[4][1].False": 1275,
    ".playerHands[3].elementVisibility[4].True": 1275,
    ".playerHands.elementVisibility[4][3].True": 1275,
    ".drawPile.components[21].color.YELLOW": 719,
    ".drawPile.components[28].color.PURPLE": 293,
    ".drawPile.components[33].color.BLUE": 544,
    ".playerHands[0].components[2].cardType.COLLECTOR": 1472,
    ".playerHands.components[2].componentName.BLUE CRAB DUO": 298,
    ".playerHands[3].elementVisibility[5][0].False": 568,
    ".drawPile.components[1].color.GREY": 368,
    ".drawPile.components[2].cardSuite.BOAT": 829,
    ".drawPile.components[3].color.WHITE": 373,
    ".drawPile.components[17].color.YELLOW": 710,
    ".drawPile.components[34].color.GREY": 284,
    ".playerHands.components[3].color.PINK": 485,
    ".playerHands.components[4].cardSuite.BOAT": 566,
    ".playerHands[2].components[0].color.WHITE": 387,
    ".playerHands[2].components[0].cardSuite.MERMAID": 387,
    ".playerHands[2].components[0].cardType.MERMAID": 387,
    ".playerHands[2].components[0].componentName.WHITE MERMAID MERMAID": 387,
    ".playerHands[2].components.color.WHITE": 1497,
    ".playerHands[2].components.cardSuite.MERMAID": 1497,
    ".playerHands[2].components.cardType.MERMAID": 1497,
    ".playerHands[2].components.componentName.WHITE MERMAID MERMAID": 1497,
    ".playerHands.elementVisibility[6].False": 1875,
    ".playerDiscards.components[2].color.YELLOW": 439,
    ".playerDiscards[2].components.cardSuite.CRAB": 1572,
    ".drawPile.components[24].componentName.BLACK BOAT DUO": 189,
    ".drawPile.components[28].cardSuite.SHELL": 462,
    ".playerHands[2].components.color.LIGHT_ORANGE": 974,
    ".playerHands[2].components[1].color.WHITE": 363,
    ".playerHands[2].components[1].cardSuite.MERMAID": 363,
    ".playerHands[2].components[1].cardType.MERMAID": 363,
    ".playerHands.components.componentName.LIGHT_ORANGE PENGUIN COLLECTOR": 1765,
    ".playerHands.components.componentName.GREY SHELL COLLECTOR": 1584,
    ".playerDiscards[3].components.color.LIGHT_BLUE": 1317,
    ".playerDiscards[3].components.color.BLACK": 809,
    ".playerDiscards.components[0].componentName.LIGHT_BLUE CRAB DUO": 524,
    ".drawPile.components[14].cardSuite.FISH": 746,
    ".drawPile.components[15].color.YELLOW": 718,
    ".lastChance.2": 170,
    ".playerHands[0].components.color.LIGHT_ORANGE": 983,
    ".playerHands.components.componentName.LIGHT_ORANGE SAILOR MULTIPLIER": 1424,
    ".playerDiscards[0].components[0].cardSuite.BOAT": 543,
    ".playerDiscards[0].components.cardSuite.BOAT": 1702,
    ".playerDiscards.components[5].color.LIGHT_BLUE": 200,
    ".drawPile.components[11].color.YELLOW": 727,
    ".turnOwner.1": 953,
    ".discardPile2.components[0].color.BLUE": 454,
    ".drawPile.components[13].cardSuite.SHARK": 483,
    ".roundCounter.2": 1174,
    ".firstPlayer.2": 875,
    ".playerHands[1].components[0].cardSuite.SHELL": 596,
    ".playerHands[1].components.cardSuite.SHELL": 2390,
    ".drawPile.components[31].cardSuite.CRAB": 614,
    ".drawPile.components[46].color.BLACK": 237,
    ".playerHands[0].components.componentName.BLACK SHELL COLLECTOR": 420,
    ".playerHands[2].components[2].color.WHITE": 316,
    ".playerHands[2].components[2].cardSuite.MERMAID": 316,
    ".playerHands[2].components[2].cardType.MERMAID": 316,
    ".playerHands[2].components[2].componentName.WHITE MERMAID MERMAID": 316,
    ".playerHands[3].components.componentName.YELLOW CRAB DUO": 410,
    ".playerHands[2].components[3].cardSuite.MERMAID": 215,
    ".drawPile.components[16].color.LIGHT_BLUE": 965,
    ".drawPile.components[28].color.GREY": 313,
    ".drawPile.components[40].color.YELLOW": 326,
    ".playerHands.components.componentName.BLACK CRAB DUO": 853,
    ".playerHands[2].components[4].color.WHITE": 136,
    ".playerHands[2].components[4].componentName.WHITE MERMAID MERMAID": 136,
    ".playerHands[3].components.cardType.MULTIPLIER": 1457,
    ".playerDiscards[1].components[0].cardType.DUO": 1927,
    ".playerDiscards[1].components[0].type.CARD": 1927,
    ".playerDiscards[1].components.cardType.DUO": 5386,
    ".playerDiscards[1].components.type.CARD": 5386,
    ".playerDiscards[1].components.color.BLUE": 1231,
    ".playerDiscards.components[0].color.PURPLE": 523,
    ".playerDiscards.components[0].componentName.PURPLE SHARK DUO": 523,
    ".playerDiscards.components.color.PURPLE": 728,
    ".playerDiscards.components.componentName.BLUE SWIMMER DUO": 719,
    ".drawPile.components[31].cardSuite.OCTOPUS": 337,
    ".playerHands[3].components[1].cardType.MULTIPLIER": 360,
    ".playerDiscards[1].components[1].cardSuite.BOAT": 396,
    ".playerHands.components[3].cardSuite.SHELL": 1373,
    ".playerHands[1].components[2].color.WHITE": 276,
    ".playerHands[1].components[2].cardSuite.MERMAID": 276,
    ".playerHands[1].components[2].cardType.MERMAID": 276,
    ".playerHands[2].components.color.PURPLE": 1256,
    ".lastChance.1": 123,
    ".playerHands[0].elementVisibility[5][0].True": 643,
    ".playerHands[0].elementVisibility[5][3].False": 643,
    ".playerHands[1].components.componentName.GREY FISH MULTIPLIER": 474,
    ".drawPile.components[29].cardSuite.BOAT": 638,
    ".firstPlayer.1": 952,
    ".drawPile.components[22].color.PURPLE": 338,
    ".playerHands[0].components.cardSuite.PENGUIN": 1811,
    ".playerHands[2].components.color.YELLOW": 2172,
    ".playerHands[2].components[1].cardSuite.OCTOPUS": 447,
    ".playerHands[2].components[2].color.GREY": 247,
    ".playerHands[2].components[2].cardSuite.OCTOPUS": 382,
    ".playerDiscards.components.componentName.LIGHT_BLUE FISH DUO": 561,
    ".drawPile.components[17].componentName.YELLOW BOAT DUO": 158,
    ".playerHands[1].components[2].color.ORANGE": 54,
    ".playerHands[1].components[2].componentName.ORANGE SAILOR COLLECTOR": 54,
    ".playerHands[3].components[4].cardSuite.SHELL": 181,
    ".discardPile2.components.cardType.MULTIPLIER": 372,
    ".drawPile.components[26].componentName.WHITE MERMAID MERMAID": 340,
    ".discardPile2.components.cardSuite.SHARK": 687,
    ".drawPile.components[24].cardSuite.PENGUIN": 306,
    ".playerHands[1].components[0].cardSuite.SHARK": 300,
    ".playerHands[1].components.cardSuite.SHARK": 892,
    ".playerHands[1].components.componentName.PURPLE SHARK DUO": 152,
    ".drawPile.components[17].cardType.MULTIPLIER": 362,
    ".playerHands[2].components[2].cardSuite.FISH": 362,
    ".playerDiscards[1].components.color.LIGHT_BLUE": 1299,
    ".discardPile1.components[0].cardSuite.SWIMMER": 538,
    ".playerHands[1].components.color.BLACK": 1759,
    ".playerHands[1].components.componentName.BLACK FISH DUO": 472,
    ".playerHands[2].elementVisibility[5].True": 524,
    ".playerHands[2].components[5].type.CARD": 524,
    ".playerHands.elementVisibility[5][2].True": 524,
    ".playerHands[0].components.cardSuite.SHARK": 918,
    ".playerDiscards[0].components.componentName.BLUE BOAT DUO": 446,
    ".playerDiscards[3].components[1].cardSuite.SWIMMER": 662,
    ".drawPile.components[4].componentName.BLACK BOAT DUO": 158,
    ".playerHands[1].components[2].color.BLACK": 342,
    ".discardPile1.components.cardSuite.SAILOR": 482,
    ".lastChance.0": 466,
    ".playerHands[3].components.cardSuite.PENGUIN": 1580,
    ".playerDiscards.components.componentName.BLACK BOAT DUO": 1308,
    ".drawPile.components[45].cardSuite.CRAB": 320,
    ".drawPile.components[2].cardSuite.SAILOR": 277,
    ".playerHands[1].components[3].color.WHITE": 213,
    ".playerHands[1].components[3].cardSuite.MERMAID": 213,
    ".playerHands[1].components[3].cardType.MERMAID": 213,
    ".playerHands[2].components.componentName.LIGHT_BLUE SHELL COLLECTOR": 369,
    ".playerHands.components.componentName.LIGHT_BLUE SHELL COLLECTOR": 1568,
    ".playerHands[0].components.componentName.GREY OCTOPUS COLLECTOR": 439,
    ".playerDiscards[1].components.componentName.BLUE BOAT DUO": 258,
    ".playerDiscards[1].components.color.BLACK": 906,
    ".drawPile.components[9].componentName.BLUE FISH DUO": 154,
    ".drawPile.components[46].cardSuite.OCTOPUS": 168,
    ".drawPile.components[31].color.GREY": 248,
    ".playerHands[0].components.componentName.BLUE CRAB DUO": 379,
    ".playerDiscards.components[0].componentName.BLUE SHARK DUO": 613,
    ".playerDiscards[1].components[1].cardSuite.CRAB": 489,
    ".drawPile.components[25].componentName.YELLOW SWIMMER DUO": 73,
    ".playerDiscards.components.componentName.LIGHT_ORANGE SWIMMER DUO": 752,
    ".playerHands.components.componentName.LIGHT_BLUE FISH DUO": 925,
    ".playerDiscards[1].components[1].cardSuite.FISH": 388,
    ".playerDiscards[1].components.componentName.BLUE FISH DUO": 316,
    ".playerHands[0].components[3].color.GREEN": 225,
    ".playerHands.components[1].componentName.LIGHT_BLUE FISH DUO": 233,
    ".playerDiscards.components.color.GREY": 551,
    ".playerDiscards.components.componentName.GREY CRAB DUO": 551,
    ".playerDiscards[3].components[1].color.LIGHT_BLUE": 528,
    ".playerHands[1].components[0].componentName.BLACK BOAT DUO": 155,
    ".playerHands[0].components.componentName.PURPLE PENGUIN COLLECTOR": 516,
    ".drawPile.components[7].componentName.YELLOW FISH DUO": 77,
    ".playerDiscards.components.componentName.YELLOW SWIMMER DUO": 731,
    ".playerHands[0].components[4].cardSuite.PENGUIN": 170,
    ".drawPile.components[46].componentName.WHITE MERMAID MERMAID": 120,
    ".playerHands[3].components.componentName.LIGHT_BLUE OCTOPUS COLLECTOR": 438,
    ".drawPile.components[6].componentName.BLUE CRAB DUO": 198,
    ".drawPile.components[11].componentName.BLACK SHELL COLLECTOR": 77,
    ".playerHands[2].components[5].cardType.MERMAID": 64,
    ".playerDiscards[2].components[1].componentName.LIGHT_BLUE BOAT DUO": 94,
    ".playerHands[0].components[4].color.GREEN": 122,
    ".playerHands[0].components.componentName.GREEN SHELL COLLECTOR": 315,
    ".playerDiscards[1].components[1].componentName.YELLOW SWIMMER DUO": 118
}